mani/__init__.py
mani/job.py
mani/run_at.py
mani/scheduler.py
mani/util.py
mani-0.3.1.dist-info/LICENSE.txt
mani-0.3.1.dist-info/METADATA
mani-0.3.1.dist-info/WHEEL
mani-0.3.1.dist-info/top_level.txt
mani-0.3.1.dist-info/RECORD
