Metadata-Version: 2.1
Name: mani
Version: 0.3.1
Summary: Distributed cron
Home-page: https://github.com/sherinkurian/mani
Author: Sherin Kurian
Author-email: sherinkurian.123@gmail.com
License: UNKNOWN
Download-URL: https://github.com/sherinkurian/mani/tarball/0.1
Keywords: cron,distributed,redis
Platform: UNKNOWN
Classifier: Environment :: Console
Classifier: Intended Audience :: Developers
Classifier: Operating System :: Unix
Classifier: Operating System :: POSIX
Classifier: Programming Language :: Python
Classifier: Topic :: System
Classifier: Topic :: Software Development
Classifier: Development Status :: 4 - Beta
Requires-Dist: redis
Requires-Dist: python-redis-lock
Requires-Dist: pytz
